days360/__init__.py
days360/days360.py
days360/py.typed
days360-1.0.2.dist-info/LICENSE.txt
days360-1.0.2.dist-info/METADATA
days360-1.0.2.dist-info/WHEEL
days360-1.0.2.dist-info/RECORD
