Metadata-Version: 2.1
Name: days360
Version: 1.0.2
Summary: Excel's DAYS360() formula for python.
Home-page: https://github.com/tfeldmann/days360
License: MIT
Keywords: excel,formula,finance,days360
Author: Thomas Feldmann
Author-email: mail@tfeldmann.de
Requires-Python: >=3.8,<4.0
Classifier: Development Status :: 5 - Production/Stable
Classifier: License :: OSI Approved :: MIT License
Classifier: Operating System :: OS Independent
Classifier: Programming Language :: Python :: 3
Classifier: Programming Language :: Python :: 3.8
Classifier: Programming Language :: Python :: 3.9
Classifier: Programming Language :: Python :: 3.10
Classifier: Programming Language :: Python :: 3.11
Classifier: Typing :: Typed
Project-URL: Repository, https://github.com/tfeldmann/days360
